_2ch_downloader.py
2ch_downloader-0.0.3.dist-info/LICENSE
2ch_downloader-0.0.3.dist-info/METADATA
2ch_downloader-0.0.3.dist-info/WHEEL
2ch_downloader-0.0.3.dist-info/entry_points.txt
2ch_downloader-0.0.3.dist-info/top_level.txt
2ch_downloader-0.0.3.dist-info/RECORD
