Metadata-Version: 2.1
Name: 2ch-downloader
Version: 0.0.3
Summary: Download all files of 2ch.hk thread.
Home-page: https://github.com/Layerex/2ch-downloader
Author: Layerex
Author-email: layerex@dismail.de
Classifier: Development Status :: 6 - Mature
Classifier: Environment :: Web Environment
Classifier: Programming Language :: Python :: 3
Classifier: License :: OSI Approved :: GNU General Public License v3 (GPLv3)
Classifier: Operating System :: OS Independent
Classifier: Topic :: Utilities
License-File: LICENSE
Requires-Dist: requests
